lndpy/__init__.py
lndpy/lnd.py
lndpy/services/__init__.py
lndpy/services/autopilot_pb2_grpc.py
lndpy/services/chainnotifier_pb2_grpc.py
lndpy/services/invoices_pb2_grpc.py
lndpy/services/lightning_pb2.py
lndpy/services/lightning_pb2_grpc.py
lndpy/services/lncli_pb2_grpc.py
lndpy/services/router_pb2_grpc.py
lndpy/services/signer_pb2_grpc.py
lndpy/services/verrpc_pb2_grpc.py
lndpy/services/walletkit_pb2_grpc.py
lndpy/services/watchtower_pb2_grpc.py
lndpy/services/wtclient_pb2_grpc.py
lndpy/services/autopilotrpc/__init__.py
lndpy/services/autopilotrpc/autopilot_pb2.py
lndpy/services/chainrpc/__init__.py
lndpy/services/chainrpc/chainnotifier_pb2.py
lndpy/services/invoicesrpc/__init__.py
lndpy/services/invoicesrpc/invoices_pb2.py
lndpy/services/lnclipb/__init__.py
lndpy/services/lnclipb/lncli_pb2.py
lndpy/services/routerrpc/__init__.py
lndpy/services/routerrpc/router_pb2.py
lndpy/services/signrpc/__init__.py
lndpy/services/signrpc/signer_pb2.py
lndpy/services/verrpc/__init__.py
lndpy/services/verrpc/verrpc_pb2.py
lndpy/services/walletrpc/__init__.py
lndpy/services/walletrpc/walletkit_pb2.py
lndpy/services/watchtowerrpc/__init__.py
lndpy/services/watchtowerrpc/watchtower_pb2.py
lndpy/services/wtclientrpc/__init__.py
lndpy/services/wtclientrpc/wtclient_pb2.py
lndpy/tests/__init__.py
lndpy/tests/test_lndpy.py
utils/__init__.py
utils/build_protos.py
lndpy-0.1.0.dist-info/LICENSE
lndpy-0.1.0.dist-info/METADATA
lndpy-0.1.0.dist-info/WHEEL
lndpy-0.1.0.dist-info/top_level.txt
lndpy-0.1.0.dist-info/RECORD
