Metadata-Version: 2.1
Name: lndpy
Version: 0.1.0
Summary: Modern pythonic bindings for the lightning network daemon 
Home-page: https://github.com/yuvadm/lndpy
Author: Yuval Adam
Author-email: _@yuv.al
License: MIT
Project-URL: Bug Tracker, https://github.com/yuvadm/lndpy/issues
Platform: UNKNOWN
Classifier: Programming Language :: Python :: 3
Classifier: Development Status :: 5 - Production/Stable
Classifier: License :: OSI Approved :: MIT License
Classifier: Operating System :: OS Independent
Requires-Python: >=3.6
License-File: LICENSE
Requires-Dist: grpcio
Requires-Dist: grpcio-tools
Requires-Dist: googleapis-common-protos
